spikee/__init__.py
spikee/cli.py
spikee/generator.py
spikee/judge.py
spikee/list.py
spikee/results.py
spikee/tester.py
spikee/attacks/anti_spotlighting.py
spikee/attacks/best_of_n.py
spikee/attacks/prompt_decomposition.py
spikee/attacks/random_suffix_search.py
spikee/data/workspace/env-example
spikee/data/workspace/attacks/sample_attack.py
spikee/data/workspace/datasets/seeds-cybersec-2025-04/README.md
spikee/data/workspace/datasets/seeds-cybersec-2025-04/adv_suffixes.jsonl
spikee/data/workspace/datasets/seeds-cybersec-2025-04/base_user_inputs.jsonl
spikee/data/workspace/datasets/seeds-cybersec-2025-04/instructions.jsonl
spikee/data/workspace/datasets/seeds-cybersec-2025-04/jailbreaks.jsonl
spikee/data/workspace/datasets/seeds-cybersec-2025-04/standalone_user_inputs.jsonl
spikee/data/workspace/datasets/seeds-cybersec-2025-04/system_messages.toml
spikee/data/workspace/datasets/seeds-empty/base_user_inputs.jsonl
spikee/data/workspace/datasets/seeds-empty/instructions.jsonl
spikee/data/workspace/datasets/seeds-empty/jailbreaks.jsonl
spikee/data/workspace/datasets/seeds-empty/standalone_user_inputs.jsonl
spikee/data/workspace/datasets/seeds-empty/system_messages.toml
spikee/data/workspace/datasets/seeds-in-the-wild-jailbreak-prompts/README.md
spikee/data/workspace/datasets/seeds-in-the-wild-jailbreak-prompts/base_user_inputs.jsonl
spikee/data/workspace/datasets/seeds-in-the-wild-jailbreak-prompts/fetch_and_convert_dataset.py
spikee/data/workspace/datasets/seeds-in-the-wild-jailbreak-prompts/instructions.jsonl
spikee/data/workspace/datasets/seeds-in-the-wild-jailbreak-prompts/jailbreaks.jsonl
spikee/data/workspace/datasets/seeds-investment-advice/README.md
spikee/data/workspace/datasets/seeds-investment-advice/base_user_inputs.jsonl
spikee/data/workspace/datasets/seeds-investment-advice/instructions.jsonl
spikee/data/workspace/datasets/seeds-investment-advice/jailbreaks.jsonl
spikee/data/workspace/datasets/seeds-investment-advice/standalone_user_inputs.jsonl
spikee-0.5.4.dist-info/licenses/LICENSE.txt
spikee-0.5.4.dist-info/METADATA
spikee-0.5.4.dist-info/WHEEL
spikee-0.5.4.dist-info/entry_points.txt
spikee-0.5.4.dist-info/top_level.txt
spikee-0.5.4.dist-info/RECORD
