Metadata-Version: 2.4
Name: spikee
Version: 0.5.4
Summary: Spikee - Simple Prompt Injection Kit for Evaluation and Exploitation
Author-email: Reversec <donato.capitella@reversec.com>
License: Apache-2.0
Keywords: prompt-injection,LLM,cyber-security,pentesting
Classifier: Programming Language :: Python :: 3
Classifier: License :: OSI Approved :: Apache Software License
Classifier: Operating System :: OS Independent
License-File: LICENSE.txt
Requires-Dist: tqdm
Requires-Dist: rich
Requires-Dist: six
Requires-Dist: toml
Requires-Dist: openai
Requires-Dist: huggingface_hub
Requires-Dist: datasets
Requires-Dist: langchain
Requires-Dist: langchain_openai
Requires-Dist: langchain-google-genai
Requires-Dist: langchain-anthropic
Requires-Dist: langchain-together
Requires-Dist: langchain-groq
Requires-Dist: langchain-aws
Requires-Dist: langchain-ollama
Requires-Dist: tabulate
Requires-Dist: jinja2
Requires-Dist: pandas
Requires-Dist: openpyxl
Requires-Dist: boto3
Requires-Dist: azure-ai-inference
Requires-Dist: python-dotenv
Requires-Dist: azure-ai-contentsafety
Requires-Dist: InquirerPy
Requires-Dist: fpdf
Requires-Dist: python-docx
Requires-Dist: toml
Provides-Extra: huggingface
Requires-Dist: langchain-huggingface; extra == "huggingface"
Dynamic: license-file
